[{"path":"src/main/java/Task.java","fileType":"java","lines":[{"lineNumber":1,"author":{"gitId":"rizrn"},"content":"public class Task {","lastModifiedDate":"2025-08-22T16:18:20","isFullCredit":false},{"lineNumber":2,"author":{"gitId":"rizrn"},"content":"    private String name;","lastModifiedDate":"2025-08-22T16:58:27","isFullCredit":false},{"lineNumber":3,"author":{"gitId":"rizrn"},"content":"","lastModifiedDate":"2025-08-22T16:58:27","isFullCredit":false},{"lineNumber":4,"author":{"gitId":"rizrn"},"content":"    public Task(String name) {","lastModifiedDate":"2025-08-22T16:58:27","isFullCredit":false},{"lineNumber":5,"author":{"gitId":"rizrn"},"content":"        this.name \u003d name;","lastModifiedDate":"2025-08-22T16:58:27","isFullCredit":false},{"lineNumber":6,"author":{"gitId":"rizrn"},"content":"    }","lastModifiedDate":"2025-08-22T16:58:27","isFullCredit":false},{"lineNumber":7,"author":{"gitId":"rizrn"},"content":"","lastModifiedDate":"2025-08-22T16:58:27","isFullCredit":false},{"lineNumber":8,"author":{"gitId":"rizrn"},"content":"    @Override","lastModifiedDate":"2025-08-22T16:58:27","isFullCredit":false},{"lineNumber":9,"author":{"gitId":"rizrn"},"content":"    public String toString() {","lastModifiedDate":"2025-08-22T16:58:27","isFullCredit":false},{"lineNumber":10,"author":{"gitId":"rizrn"},"content":"        return this.name;","lastModifiedDate":"2025-08-22T16:58:27","isFullCredit":false},{"lineNumber":11,"author":{"gitId":"rizrn"},"content":"    }","lastModifiedDate":"2025-08-22T16:58:27","isFullCredit":false},{"lineNumber":12,"author":{"gitId":"rizrn"},"content":"}","lastModifiedDate":"2025-08-22T16:18:20","isFullCredit":false}],"authorContributionMap":{"rizrn":12}},{"path":"src/main/java/TaskList.java","fileType":"java","lines":[{"lineNumber":1,"author":{"gitId":"rizrn"},"content":"import java.lang.StringBuffer;","lastModifiedDate":"2025-08-22T16:58:27","isFullCredit":false},{"lineNumber":2,"author":{"gitId":"rizrn"},"content":"public class TaskList {","lastModifiedDate":"2025-08-22T16:18:20","isFullCredit":false},{"lineNumber":3,"author":{"gitId":"rizrn"},"content":"    private static final int MAX_SIZE \u003d 100;","lastModifiedDate":"2025-08-22T16:58:27","isFullCredit":false},{"lineNumber":4,"author":{"gitId":"rizrn"},"content":"    private Task[] tasks;","lastModifiedDate":"2025-08-22T16:58:27","isFullCredit":false},{"lineNumber":5,"author":{"gitId":"rizrn"},"content":"    private int size;","lastModifiedDate":"2025-08-22T16:58:27","isFullCredit":false},{"lineNumber":6,"author":{"gitId":"rizrn"},"content":"","lastModifiedDate":"2025-08-22T16:58:27","isFullCredit":false},{"lineNumber":7,"author":{"gitId":"rizrn"},"content":"    public TaskList() {","lastModifiedDate":"2025-08-22T16:58:27","isFullCredit":false},{"lineNumber":8,"author":{"gitId":"rizrn"},"content":"        this.tasks \u003d new Task[MAX_SIZE];","lastModifiedDate":"2025-08-22T16:58:27","isFullCredit":false},{"lineNumber":9,"author":{"gitId":"rizrn"},"content":"        this.size \u003d 0;","lastModifiedDate":"2025-08-22T16:58:27","isFullCredit":false},{"lineNumber":10,"author":{"gitId":"rizrn"},"content":"    }","lastModifiedDate":"2025-08-22T16:58:27","isFullCredit":false},{"lineNumber":11,"author":{"gitId":"rizrn"},"content":"    public void addTask(String name) {","lastModifiedDate":"2025-08-22T16:58:27","isFullCredit":false},{"lineNumber":12,"author":{"gitId":"rizrn"},"content":"        Task t \u003d new Task(name);","lastModifiedDate":"2025-08-22T16:58:27","isFullCredit":false},{"lineNumber":13,"author":{"gitId":"rizrn"},"content":"        this.tasks[this.size++] \u003d t;","lastModifiedDate":"2025-08-22T16:58:27","isFullCredit":false},{"lineNumber":14,"author":{"gitId":"rizrn"},"content":"    }","lastModifiedDate":"2025-08-22T16:58:27","isFullCredit":false},{"lineNumber":15,"author":{"gitId":"rizrn"},"content":"","lastModifiedDate":"2025-08-22T16:58:27","isFullCredit":false},{"lineNumber":16,"author":{"gitId":"rizrn"},"content":"    @Override","lastModifiedDate":"2025-08-22T16:58:27","isFullCredit":false},{"lineNumber":17,"author":{"gitId":"rizrn"},"content":"    public String toString() {","lastModifiedDate":"2025-08-22T16:58:27","isFullCredit":false},{"lineNumber":18,"author":{"gitId":"rizrn"},"content":"        StringBuffer sb \u003d new StringBuffer();","lastModifiedDate":"2025-08-22T16:58:27","isFullCredit":false},{"lineNumber":19,"author":{"gitId":"rizrn"},"content":"        for (int i \u003d 0; i \u003c this.size; i++) {","lastModifiedDate":"2025-08-22T16:58:27","isFullCredit":false},{"lineNumber":20,"author":{"gitId":"rizrn"},"content":"            String newLine \u003d (i + 1) + \" \" + this.tasks[i]; //increment i by 1 to start at 1","lastModifiedDate":"2025-08-22T17:10:30","isFullCredit":false},{"lineNumber":21,"author":{"gitId":"rizrn"},"content":"            sb.append(newLine);","lastModifiedDate":"2025-08-22T16:58:27","isFullCredit":false},{"lineNumber":22,"author":{"gitId":"rizrn"},"content":"            sb.append(\"\\n\");","lastModifiedDate":"2025-08-22T16:58:27","isFullCredit":false},{"lineNumber":23,"author":{"gitId":"rizrn"},"content":"        }","lastModifiedDate":"2025-08-22T16:58:27","isFullCredit":false},{"lineNumber":24,"author":{"gitId":"rizrn"},"content":"        sb.deleteCharAt(sb.length() - 1);","lastModifiedDate":"2025-08-22T16:58:27","isFullCredit":false},{"lineNumber":25,"author":{"gitId":"rizrn"},"content":"        return sb.toString();","lastModifiedDate":"2025-08-22T16:58:27","isFullCredit":false},{"lineNumber":26,"author":{"gitId":"rizrn"},"content":"    }","lastModifiedDate":"2025-08-22T16:58:27","isFullCredit":false},{"lineNumber":27,"author":{"gitId":"rizrn"},"content":"}","lastModifiedDate":"2025-08-22T16:18:20","isFullCredit":false}],"authorContributionMap":{"rizrn":27}},{"path":"src/main/java/Woop.java","fileType":"java","lines":[{"lineNumber":1,"author":{"gitId":"rizrn"},"content":"public class Woop {","lastModifiedDate":"2025-08-22T14:19:14","isFullCredit":false},{"lineNumber":2,"author":{"gitId":"rizrn"},"content":"    public static final String name \u003d \"Woop\";","lastModifiedDate":"2025-08-22T14:19:14","isFullCredit":false},{"lineNumber":3,"author":{"gitId":"rizrn"},"content":"    public static void main(String[] args) {","lastModifiedDate":"2025-08-22T14:19:14","isFullCredit":false},{"lineNumber":4,"author":{"gitId":"rizrn"},"content":"        WoopLogic logic \u003d new WoopLogic();","lastModifiedDate":"2025-08-22T16:18:20","isFullCredit":false},{"lineNumber":5,"author":{"gitId":"rizrn"},"content":"        String startMessage \u003d \"Hello! I\u0027m \"","lastModifiedDate":"2025-08-22T14:19:14","isFullCredit":false},{"lineNumber":6,"author":{"gitId":"rizrn"},"content":"                + name + \"\\n\" +","lastModifiedDate":"2025-08-22T14:19:14","isFullCredit":false},{"lineNumber":7,"author":{"gitId":"rizrn"},"content":"                \"What can I do for you?\";","lastModifiedDate":"2025-08-22T14:19:14","isFullCredit":false},{"lineNumber":8,"author":{"gitId":"rizrn"},"content":"        String endMessage \u003d \"Bye. Hope to see you again soon!\";","lastModifiedDate":"2025-08-22T14:19:14","isFullCredit":false},{"lineNumber":9,"author":{"gitId":"rizrn"},"content":"        System.out.println(startMessage);","lastModifiedDate":"2025-08-22T14:19:14","isFullCredit":false},{"lineNumber":10,"author":{"gitId":"rizrn"},"content":"        logic.run();","lastModifiedDate":"2025-08-22T16:18:20","isFullCredit":false},{"lineNumber":11,"author":{"gitId":"rizrn"},"content":"        System.out.println(endMessage);","lastModifiedDate":"2025-08-22T14:42:34","isFullCredit":false},{"lineNumber":12,"author":{"gitId":"rizrn"},"content":"    }","lastModifiedDate":"2025-08-22T14:19:14","isFullCredit":false},{"lineNumber":13,"author":{"gitId":"rizrn"},"content":"}","lastModifiedDate":"2025-08-22T14:19:14","isFullCredit":false}],"authorContributionMap":{"rizrn":13}},{"path":"src/main/java/WoopLogic.java","fileType":"java","lines":[{"lineNumber":1,"author":{"gitId":"rizrn"},"content":"import java.util.Scanner;","lastModifiedDate":"2025-08-22T16:18:20","isFullCredit":false},{"lineNumber":2,"author":{"gitId":"rizrn"},"content":"public class WoopLogic {","lastModifiedDate":"2025-08-22T16:18:20","isFullCredit":false},{"lineNumber":3,"author":{"gitId":"rizrn"},"content":"    private final Scanner sc;","lastModifiedDate":"2025-08-22T16:18:20","isFullCredit":false},{"lineNumber":4,"author":{"gitId":"rizrn"},"content":"    private static final String EXIT \u003d \"bye\";","lastModifiedDate":"2025-08-22T16:58:27","isFullCredit":false},{"lineNumber":5,"author":{"gitId":"rizrn"},"content":"    private TaskList taskList;","lastModifiedDate":"2025-08-22T16:58:27","isFullCredit":false},{"lineNumber":6,"author":{"gitId":"rizrn"},"content":"","lastModifiedDate":"2025-08-22T16:58:27","isFullCredit":false},{"lineNumber":7,"author":{"gitId":"rizrn"},"content":"    public WoopLogic() {","lastModifiedDate":"2025-08-22T16:18:20","isFullCredit":false},{"lineNumber":8,"author":{"gitId":"rizrn"},"content":"        this.sc \u003d new Scanner(System.in);","lastModifiedDate":"2025-08-22T16:18:20","isFullCredit":false},{"lineNumber":9,"author":{"gitId":"rizrn"},"content":"        this.taskList \u003d new TaskList();","lastModifiedDate":"2025-08-22T16:58:27","isFullCredit":false},{"lineNumber":10,"author":{"gitId":"rizrn"},"content":"    }","lastModifiedDate":"2025-08-22T16:18:20","isFullCredit":false},{"lineNumber":11,"author":{"gitId":"rizrn"},"content":"","lastModifiedDate":"2025-08-22T16:18:20","isFullCredit":false},{"lineNumber":12,"author":{"gitId":"rizrn"},"content":"    public void run() {","lastModifiedDate":"2025-08-22T16:18:20","isFullCredit":false},{"lineNumber":13,"author":{"gitId":"rizrn"},"content":"        String userInput \u003d this.sc.nextLine();","lastModifiedDate":"2025-08-22T16:18:20","isFullCredit":false},{"lineNumber":14,"author":{"gitId":"rizrn"},"content":"","lastModifiedDate":"2025-08-22T16:58:27","isFullCredit":false},{"lineNumber":15,"author":{"gitId":"rizrn"},"content":"        while (!checkExit(userInput)) {","lastModifiedDate":"2025-08-22T16:18:20","isFullCredit":false},{"lineNumber":16,"author":{"gitId":"rizrn"},"content":"            switch (userInput) {","lastModifiedDate":"2025-08-22T17:05:47","isFullCredit":false},{"lineNumber":17,"author":{"gitId":"rizrn"},"content":"                case \"list\":","lastModifiedDate":"2025-08-22T17:05:47","isFullCredit":false},{"lineNumber":18,"author":{"gitId":"rizrn"},"content":"                    System.out.println(this.taskList);","lastModifiedDate":"2025-08-22T17:05:47","isFullCredit":false},{"lineNumber":19,"author":{"gitId":"rizrn"},"content":"                    break;","lastModifiedDate":"2025-08-22T17:05:47","isFullCredit":false},{"lineNumber":20,"author":{"gitId":"rizrn"},"content":"                default:","lastModifiedDate":"2025-08-22T17:05:47","isFullCredit":false},{"lineNumber":21,"author":{"gitId":"rizrn"},"content":"                    this.taskList.addTask(userInput);","lastModifiedDate":"2025-08-22T16:58:27","isFullCredit":false},{"lineNumber":22,"author":{"gitId":"rizrn"},"content":"                    System.out.println(\"added \" + userInput);","lastModifiedDate":"2025-08-22T16:58:27","isFullCredit":false},{"lineNumber":23,"author":{"gitId":"rizrn"},"content":"            }","lastModifiedDate":"2025-08-22T17:05:47","isFullCredit":false},{"lineNumber":24,"author":{"gitId":"rizrn"},"content":"","lastModifiedDate":"2025-08-22T17:05:47","isFullCredit":false},{"lineNumber":25,"author":{"gitId":"rizrn"},"content":"            userInput \u003d this.sc.nextLine();","lastModifiedDate":"2025-08-22T16:18:20","isFullCredit":false},{"lineNumber":26,"author":{"gitId":"rizrn"},"content":"        }","lastModifiedDate":"2025-08-22T16:18:20","isFullCredit":false},{"lineNumber":27,"author":{"gitId":"rizrn"},"content":"    }","lastModifiedDate":"2025-08-22T16:18:20","isFullCredit":false},{"lineNumber":28,"author":{"gitId":"rizrn"},"content":"    private boolean checkExit(String userInput) {","lastModifiedDate":"2025-08-22T16:18:20","isFullCredit":false},{"lineNumber":29,"author":{"gitId":"rizrn"},"content":"        return userInput.equals(EXIT);","lastModifiedDate":"2025-08-22T16:58:27","isFullCredit":false},{"lineNumber":30,"author":{"gitId":"rizrn"},"content":"    }","lastModifiedDate":"2025-08-22T16:18:20","isFullCredit":false},{"lineNumber":31,"author":{"gitId":"rizrn"},"content":"","lastModifiedDate":"2025-08-22T16:18:20","isFullCredit":false},{"lineNumber":32,"author":{"gitId":"rizrn"},"content":"}","lastModifiedDate":"2025-08-22T16:18:20","isFullCredit":false}],"authorContributionMap":{"rizrn":32}}]
