{"authorDailyContributionsMap":{"Eugene-Lek":[{"date":"2025-08-18T00:00:00","commitResults":[{"hash":"1e161a196b047d412a1a453e87e7bccf4722e53f","isMergeCommit":false,"messageTitle":"add: rename \u0026 echo","messageBody":"","tags":["Level-1"],"fileTypesAndContributionMap":{"java":{"insertions":21,"deletions":10}}},{"hash":"34c64c813ce80b2f4a30c66301384e9ff78d5afd","isMergeCommit":false,"messageTitle":"add: level 2","messageBody":"","tags":["Level-2"],"fileTypesAndContributionMap":{"java":{"insertions":53,"deletions":1}}}]},{"date":"2025-08-21T00:00:00","commitResults":[{"hash":"42ee464ef6f4b0c7bca3c6d0c6ecf7f991ad2d33","isMergeCommit":false,"messageTitle":"add: level 3 to 6","messageBody":"","tags":["Level-6","Level-5","Level-4","Level-3","Level-0","A-TextUiTesting"],"fileTypesAndContributionMap":{"txt":{"insertions":9,"deletions":0},"java":{"insertions":262,"deletions":63},"bat":{"insertions":1,"deletions":1},"sh":{"insertions":1,"deletions":1}}}]}]},"authorFileTypeContributionMap":{"Eugene-Lek":{"java":272,"md":0,"fxml":0,"sh":1,"bat":1,"gradle":0,"txt":9}},"authorContributionVariance":{"Eugene-Lek":7763.4536},"authorDisplayNameMap":{"Eugene-Lek":"LEK ..GENE"}}
