[{"path":"src/main/java/Usagi.java","fileType":"java","lines":[{"lineNumber":1,"author":{"gitId":"cjaycee"},"content":"import java.util.Scanner;","lastModifiedDate":"2025-08-22T00:37:57","isFullCredit":false},{"lineNumber":2,"author":{"gitId":"cjaycee"},"content":"import java.util.ArrayList;","lastModifiedDate":"2025-08-22T00:53:41","isFullCredit":false},{"lineNumber":3,"author":{"gitId":"cjaycee"},"content":"import java.util.NoSuchElementException;","lastModifiedDate":"2025-08-28T16:59:27","isFullCredit":false},{"lineNumber":4,"author":{"gitId":"cjaycee"},"content":"","lastModifiedDate":"2025-08-22T00:37:57","isFullCredit":false},{"lineNumber":5,"author":{"gitId":"cjaycee"},"content":"public class Usagi {","lastModifiedDate":"2025-08-22T00:25:30","isFullCredit":false},{"lineNumber":6,"author":{"gitId":"cjaycee"},"content":"    private static final String HORIZONTAL_LINE \u003d \"____________________________________________________________\";","lastModifiedDate":"2025-08-28T16:59:27","isFullCredit":false},{"lineNumber":7,"author":{"gitId":"cjaycee"},"content":"","lastModifiedDate":"2025-08-28T16:59:27","isFullCredit":false},{"lineNumber":8,"author":{"gitId":"cjaycee"},"content":"    private static void printLine() {","lastModifiedDate":"2025-08-28T16:59:27","isFullCredit":false},{"lineNumber":9,"author":{"gitId":"cjaycee"},"content":"        System.out.println(HORIZONTAL_LINE);","lastModifiedDate":"2025-08-28T16:59:27","isFullCredit":false},{"lineNumber":10,"author":{"gitId":"cjaycee"},"content":"    }","lastModifiedDate":"2025-08-28T16:59:27","isFullCredit":false},{"lineNumber":11,"author":{"gitId":"cjaycee"},"content":"","lastModifiedDate":"2025-08-22T01:18:02","isFullCredit":false},{"lineNumber":12,"author":{"gitId":"cjaycee"},"content":"    // Custom exception classes","lastModifiedDate":"2025-08-22T02:07:02","isFullCredit":false},{"lineNumber":13,"author":{"gitId":"cjaycee"},"content":"    static class UsagiException extends Exception {","lastModifiedDate":"2025-08-22T02:07:02","isFullCredit":false},{"lineNumber":14,"author":{"gitId":"cjaycee"},"content":"        public UsagiException(String message) {","lastModifiedDate":"2025-08-22T02:07:02","isFullCredit":false},{"lineNumber":15,"author":{"gitId":"cjaycee"},"content":"            super(message);","lastModifiedDate":"2025-08-22T02:07:02","isFullCredit":false},{"lineNumber":16,"author":{"gitId":"cjaycee"},"content":"        }","lastModifiedDate":"2025-08-22T02:07:02","isFullCredit":false},{"lineNumber":17,"author":{"gitId":"cjaycee"},"content":"    }","lastModifiedDate":"2025-08-22T02:07:02","isFullCredit":false},{"lineNumber":18,"author":{"gitId":"cjaycee"},"content":"","lastModifiedDate":"2025-08-22T02:07:02","isFullCredit":false},{"lineNumber":19,"author":{"gitId":"cjaycee"},"content":"    static class EmptyDescriptionException extends UsagiException {","lastModifiedDate":"2025-08-22T02:07:02","isFullCredit":false},{"lineNumber":20,"author":{"gitId":"cjaycee"},"content":"        public EmptyDescriptionException(String taskType) {","lastModifiedDate":"2025-08-22T02:07:02","isFullCredit":false},{"lineNumber":21,"author":{"gitId":"cjaycee"},"content":"            super(\"The description of a \" + taskType + \" cannot be empty.\");","lastModifiedDate":"2025-08-22T02:07:02","isFullCredit":false},{"lineNumber":22,"author":{"gitId":"cjaycee"},"content":"        }","lastModifiedDate":"2025-08-22T02:07:02","isFullCredit":false},{"lineNumber":23,"author":{"gitId":"cjaycee"},"content":"    }","lastModifiedDate":"2025-08-22T02:07:02","isFullCredit":false},{"lineNumber":24,"author":{"gitId":"cjaycee"},"content":"","lastModifiedDate":"2025-08-22T02:07:02","isFullCredit":false},{"lineNumber":25,"author":{"gitId":"cjaycee"},"content":"    static class InvalidCommandException extends UsagiException {","lastModifiedDate":"2025-08-22T02:07:02","isFullCredit":false},{"lineNumber":26,"author":{"gitId":"cjaycee"},"content":"        public InvalidCommandException() {","lastModifiedDate":"2025-08-22T02:07:02","isFullCredit":false},{"lineNumber":27,"author":{"gitId":"cjaycee"},"content":"            super(\"I\u0027m sorry, but I don\u0027t know what that means. Please try again!\");","lastModifiedDate":"2025-08-22T02:07:02","isFullCredit":false},{"lineNumber":28,"author":{"gitId":"cjaycee"},"content":"        }","lastModifiedDate":"2025-08-22T02:07:02","isFullCredit":false},{"lineNumber":29,"author":{"gitId":"cjaycee"},"content":"    }","lastModifiedDate":"2025-08-22T02:07:02","isFullCredit":false},{"lineNumber":30,"author":{"gitId":"cjaycee"},"content":"","lastModifiedDate":"2025-08-22T02:07:02","isFullCredit":false},{"lineNumber":31,"author":{"gitId":"cjaycee"},"content":"    static class InvalidFormatException extends UsagiException {","lastModifiedDate":"2025-08-22T02:07:02","isFullCredit":false},{"lineNumber":32,"author":{"gitId":"cjaycee"},"content":"        public InvalidFormatException(String correctFormat) {","lastModifiedDate":"2025-08-22T02:07:02","isFullCredit":false},{"lineNumber":33,"author":{"gitId":"cjaycee"},"content":"            super(\"Please use the correct format: \" + correctFormat);","lastModifiedDate":"2025-08-22T02:07:02","isFullCredit":false},{"lineNumber":34,"author":{"gitId":"cjaycee"},"content":"        }","lastModifiedDate":"2025-08-22T02:07:02","isFullCredit":false},{"lineNumber":35,"author":{"gitId":"cjaycee"},"content":"    }","lastModifiedDate":"2025-08-22T02:07:02","isFullCredit":false},{"lineNumber":36,"author":{"gitId":"cjaycee"},"content":"","lastModifiedDate":"2025-08-22T02:07:02","isFullCredit":false},{"lineNumber":37,"author":{"gitId":"cjaycee"},"content":"    static class InvalidTaskNumberException extends UsagiException {","lastModifiedDate":"2025-08-22T02:07:02","isFullCredit":false},{"lineNumber":38,"author":{"gitId":"cjaycee"},"content":"        public InvalidTaskNumberException(int maxTasks) {","lastModifiedDate":"2025-08-22T02:07:02","isFullCredit":false},{"lineNumber":39,"author":{"gitId":"cjaycee"},"content":"            super(\"Please enter a valid task number between 1 and \" + maxTasks);","lastModifiedDate":"2025-08-22T02:07:02","isFullCredit":false},{"lineNumber":40,"author":{"gitId":"cjaycee"},"content":"        }","lastModifiedDate":"2025-08-22T02:07:02","isFullCredit":false},{"lineNumber":41,"author":{"gitId":"cjaycee"},"content":"    }","lastModifiedDate":"2025-08-22T02:07:02","isFullCredit":false},{"lineNumber":42,"author":{"gitId":"cjaycee"},"content":"","lastModifiedDate":"2025-08-22T02:07:02","isFullCredit":false},{"lineNumber":43,"author":{"gitId":"cjaycee"},"content":"    // Base Task class","lastModifiedDate":"2025-08-22T02:02:56","isFullCredit":false},{"lineNumber":44,"author":{"gitId":"cjaycee"},"content":"    abstract static class Task {","lastModifiedDate":"2025-08-22T02:02:56","isFullCredit":false},{"lineNumber":45,"author":{"gitId":"cjaycee"},"content":"        protected String description;","lastModifiedDate":"2025-08-22T02:02:56","isFullCredit":false},{"lineNumber":46,"author":{"gitId":"cjaycee"},"content":"        protected boolean isDone;","lastModifiedDate":"2025-08-22T02:02:56","isFullCredit":false},{"lineNumber":47,"author":{"gitId":"cjaycee"},"content":"","lastModifiedDate":"2025-08-22T01:18:02","isFullCredit":false},{"lineNumber":48,"author":{"gitId":"cjaycee"},"content":"        Task(String description) {","lastModifiedDate":"2025-08-22T01:18:02","isFullCredit":false},{"lineNumber":49,"author":{"gitId":"cjaycee"},"content":"            this.description \u003d description;","lastModifiedDate":"2025-08-22T01:18:02","isFullCredit":false},{"lineNumber":50,"author":{"gitId":"cjaycee"},"content":"            this.isDone \u003d false;","lastModifiedDate":"2025-08-22T01:18:02","isFullCredit":false},{"lineNumber":51,"author":{"gitId":"cjaycee"},"content":"        }","lastModifiedDate":"2025-08-22T01:18:02","isFullCredit":false},{"lineNumber":52,"author":{"gitId":"cjaycee"},"content":"","lastModifiedDate":"2025-08-22T01:18:02","isFullCredit":false},{"lineNumber":53,"author":{"gitId":"cjaycee"},"content":"        String getStatusIcon() {","lastModifiedDate":"2025-08-22T01:18:02","isFullCredit":false},{"lineNumber":54,"author":{"gitId":"cjaycee"},"content":"            return isDone ? \"[X]\" : \"[ ]\";","lastModifiedDate":"2025-08-22T01:18:02","isFullCredit":false},{"lineNumber":55,"author":{"gitId":"cjaycee"},"content":"        }","lastModifiedDate":"2025-08-22T01:18:02","isFullCredit":false},{"lineNumber":56,"author":{"gitId":"cjaycee"},"content":"","lastModifiedDate":"2025-08-22T01:18:02","isFullCredit":false},{"lineNumber":57,"author":{"gitId":"cjaycee"},"content":"        void markAsDone() {","lastModifiedDate":"2025-08-22T01:18:02","isFullCredit":false},{"lineNumber":58,"author":{"gitId":"cjaycee"},"content":"            this.isDone \u003d true;","lastModifiedDate":"2025-08-22T01:18:02","isFullCredit":false},{"lineNumber":59,"author":{"gitId":"cjaycee"},"content":"        }","lastModifiedDate":"2025-08-22T01:18:02","isFullCredit":false},{"lineNumber":60,"author":{"gitId":"cjaycee"},"content":"","lastModifiedDate":"2025-08-22T01:18:02","isFullCredit":false},{"lineNumber":61,"author":{"gitId":"cjaycee"},"content":"        void markAsNotDone() {","lastModifiedDate":"2025-08-22T01:18:02","isFullCredit":false},{"lineNumber":62,"author":{"gitId":"cjaycee"},"content":"            this.isDone \u003d false;","lastModifiedDate":"2025-08-22T01:18:02","isFullCredit":false},{"lineNumber":63,"author":{"gitId":"cjaycee"},"content":"        }","lastModifiedDate":"2025-08-22T01:18:02","isFullCredit":false},{"lineNumber":64,"author":{"gitId":"cjaycee"},"content":"","lastModifiedDate":"2025-08-22T01:18:02","isFullCredit":false},{"lineNumber":65,"author":{"gitId":"cjaycee"},"content":"        @Override","lastModifiedDate":"2025-08-22T01:18:02","isFullCredit":false},{"lineNumber":66,"author":{"gitId":"cjaycee"},"content":"        public String toString() {","lastModifiedDate":"2025-08-22T01:18:02","isFullCredit":false},{"lineNumber":67,"author":{"gitId":"cjaycee"},"content":"            return getStatusIcon() + \" \" + description;","lastModifiedDate":"2025-08-22T01:18:02","isFullCredit":false},{"lineNumber":68,"author":{"gitId":"cjaycee"},"content":"        }","lastModifiedDate":"2025-08-22T01:18:02","isFullCredit":false},{"lineNumber":69,"author":{"gitId":"cjaycee"},"content":"","lastModifiedDate":"2025-08-22T02:02:56","isFullCredit":false},{"lineNumber":70,"author":{"gitId":"cjaycee"},"content":"        abstract String getTaskType();","lastModifiedDate":"2025-08-22T02:02:56","isFullCredit":false},{"lineNumber":71,"author":{"gitId":"cjaycee"},"content":"        abstract String getFullDescription();","lastModifiedDate":"2025-08-22T02:02:56","isFullCredit":false},{"lineNumber":72,"author":{"gitId":"cjaycee"},"content":"    }","lastModifiedDate":"2025-08-22T02:02:56","isFullCredit":false},{"lineNumber":73,"author":{"gitId":"cjaycee"},"content":"","lastModifiedDate":"2025-08-22T02:02:56","isFullCredit":false},{"lineNumber":74,"author":{"gitId":"cjaycee"},"content":"    // Todo class","lastModifiedDate":"2025-08-22T02:02:56","isFullCredit":false},{"lineNumber":75,"author":{"gitId":"cjaycee"},"content":"    static class Todo extends Task {","lastModifiedDate":"2025-08-22T02:02:56","isFullCredit":false},{"lineNumber":76,"author":{"gitId":"cjaycee"},"content":"        Todo(String description) {","lastModifiedDate":"2025-08-22T02:02:56","isFullCredit":false},{"lineNumber":77,"author":{"gitId":"cjaycee"},"content":"            super(description);","lastModifiedDate":"2025-08-22T02:02:56","isFullCredit":false},{"lineNumber":78,"author":{"gitId":"cjaycee"},"content":"        }","lastModifiedDate":"2025-08-22T02:02:56","isFullCredit":false},{"lineNumber":79,"author":{"gitId":"cjaycee"},"content":"","lastModifiedDate":"2025-08-22T02:02:56","isFullCredit":false},{"lineNumber":80,"author":{"gitId":"cjaycee"},"content":"        @Override","lastModifiedDate":"2025-08-22T02:02:56","isFullCredit":false},{"lineNumber":81,"author":{"gitId":"cjaycee"},"content":"        String getTaskType() {","lastModifiedDate":"2025-08-22T02:02:56","isFullCredit":false},{"lineNumber":82,"author":{"gitId":"cjaycee"},"content":"            return \"[T]\";","lastModifiedDate":"2025-08-22T02:02:56","isFullCredit":false},{"lineNumber":83,"author":{"gitId":"cjaycee"},"content":"        }","lastModifiedDate":"2025-08-22T02:02:56","isFullCredit":false},{"lineNumber":84,"author":{"gitId":"cjaycee"},"content":"","lastModifiedDate":"2025-08-22T02:02:56","isFullCredit":false},{"lineNumber":85,"author":{"gitId":"cjaycee"},"content":"        @Override","lastModifiedDate":"2025-08-22T02:02:56","isFullCredit":false},{"lineNumber":86,"author":{"gitId":"cjaycee"},"content":"        String getFullDescription() {","lastModifiedDate":"2025-08-22T02:02:56","isFullCredit":false},{"lineNumber":87,"author":{"gitId":"cjaycee"},"content":"            return getTaskType() + super.toString();","lastModifiedDate":"2025-08-22T02:02:56","isFullCredit":false},{"lineNumber":88,"author":{"gitId":"cjaycee"},"content":"        }","lastModifiedDate":"2025-08-22T02:02:56","isFullCredit":false},{"lineNumber":89,"author":{"gitId":"cjaycee"},"content":"","lastModifiedDate":"2025-08-22T02:02:56","isFullCredit":false},{"lineNumber":90,"author":{"gitId":"cjaycee"},"content":"        @Override","lastModifiedDate":"2025-08-22T02:02:56","isFullCredit":false},{"lineNumber":91,"author":{"gitId":"cjaycee"},"content":"        public String toString() {","lastModifiedDate":"2025-08-22T02:02:56","isFullCredit":false},{"lineNumber":92,"author":{"gitId":"cjaycee"},"content":"            return getFullDescription();","lastModifiedDate":"2025-08-22T02:02:56","isFullCredit":false},{"lineNumber":93,"author":{"gitId":"cjaycee"},"content":"        }","lastModifiedDate":"2025-08-22T02:02:56","isFullCredit":false},{"lineNumber":94,"author":{"gitId":"cjaycee"},"content":"    }","lastModifiedDate":"2025-08-22T02:02:56","isFullCredit":false},{"lineNumber":95,"author":{"gitId":"cjaycee"},"content":"","lastModifiedDate":"2025-08-22T02:02:56","isFullCredit":false},{"lineNumber":96,"author":{"gitId":"cjaycee"},"content":"    // Deadline class","lastModifiedDate":"2025-08-22T02:02:56","isFullCredit":false},{"lineNumber":97,"author":{"gitId":"cjaycee"},"content":"    static class Deadline extends Task {","lastModifiedDate":"2025-08-22T02:02:56","isFullCredit":false},{"lineNumber":98,"author":{"gitId":"cjaycee"},"content":"        protected String by;","lastModifiedDate":"2025-08-22T02:02:56","isFullCredit":false},{"lineNumber":99,"author":{"gitId":"cjaycee"},"content":"","lastModifiedDate":"2025-08-22T02:02:56","isFullCredit":false},{"lineNumber":100,"author":{"gitId":"cjaycee"},"content":"        Deadline(String description, String by) {","lastModifiedDate":"2025-08-22T02:02:56","isFullCredit":false},{"lineNumber":101,"author":{"gitId":"cjaycee"},"content":"            super(description);","lastModifiedDate":"2025-08-22T02:02:56","isFullCredit":false},{"lineNumber":102,"author":{"gitId":"cjaycee"},"content":"            this.by \u003d by;","lastModifiedDate":"2025-08-22T02:02:56","isFullCredit":false},{"lineNumber":103,"author":{"gitId":"cjaycee"},"content":"        }","lastModifiedDate":"2025-08-22T02:02:56","isFullCredit":false},{"lineNumber":104,"author":{"gitId":"cjaycee"},"content":"","lastModifiedDate":"2025-08-22T02:02:56","isFullCredit":false},{"lineNumber":105,"author":{"gitId":"cjaycee"},"content":"        @Override","lastModifiedDate":"2025-08-22T02:02:56","isFullCredit":false},{"lineNumber":106,"author":{"gitId":"cjaycee"},"content":"        String getTaskType() {","lastModifiedDate":"2025-08-22T02:02:56","isFullCredit":false},{"lineNumber":107,"author":{"gitId":"cjaycee"},"content":"            return \"[D]\";","lastModifiedDate":"2025-08-22T02:02:56","isFullCredit":false},{"lineNumber":108,"author":{"gitId":"cjaycee"},"content":"        }","lastModifiedDate":"2025-08-22T02:02:56","isFullCredit":false},{"lineNumber":109,"author":{"gitId":"cjaycee"},"content":"","lastModifiedDate":"2025-08-22T02:02:56","isFullCredit":false},{"lineNumber":110,"author":{"gitId":"cjaycee"},"content":"        @Override","lastModifiedDate":"2025-08-22T02:02:56","isFullCredit":false},{"lineNumber":111,"author":{"gitId":"cjaycee"},"content":"        String getFullDescription() {","lastModifiedDate":"2025-08-22T02:02:56","isFullCredit":false},{"lineNumber":112,"author":{"gitId":"cjaycee"},"content":"            return getTaskType() + super.toString() + \" (by: \" + by + \")\";","lastModifiedDate":"2025-08-22T02:02:56","isFullCredit":false},{"lineNumber":113,"author":{"gitId":"cjaycee"},"content":"        }","lastModifiedDate":"2025-08-22T02:02:56","isFullCredit":false},{"lineNumber":114,"author":{"gitId":"cjaycee"},"content":"","lastModifiedDate":"2025-08-22T02:02:56","isFullCredit":false},{"lineNumber":115,"author":{"gitId":"cjaycee"},"content":"        @Override","lastModifiedDate":"2025-08-22T02:02:56","isFullCredit":false},{"lineNumber":116,"author":{"gitId":"cjaycee"},"content":"        public String toString() {","lastModifiedDate":"2025-08-22T02:02:56","isFullCredit":false},{"lineNumber":117,"author":{"gitId":"cjaycee"},"content":"            return getFullDescription();","lastModifiedDate":"2025-08-22T02:02:56","isFullCredit":false},{"lineNumber":118,"author":{"gitId":"cjaycee"},"content":"        }","lastModifiedDate":"2025-08-22T02:02:56","isFullCredit":false},{"lineNumber":119,"author":{"gitId":"cjaycee"},"content":"    }","lastModifiedDate":"2025-08-22T02:02:56","isFullCredit":false},{"lineNumber":120,"author":{"gitId":"cjaycee"},"content":"","lastModifiedDate":"2025-08-22T02:02:56","isFullCredit":false},{"lineNumber":121,"author":{"gitId":"cjaycee"},"content":"    // Event class","lastModifiedDate":"2025-08-22T02:02:56","isFullCredit":false},{"lineNumber":122,"author":{"gitId":"cjaycee"},"content":"    static class Event extends Task {","lastModifiedDate":"2025-08-22T02:02:56","isFullCredit":false},{"lineNumber":123,"author":{"gitId":"cjaycee"},"content":"        protected String from;","lastModifiedDate":"2025-08-22T02:02:56","isFullCredit":false},{"lineNumber":124,"author":{"gitId":"cjaycee"},"content":"        protected String to;","lastModifiedDate":"2025-08-22T02:02:56","isFullCredit":false},{"lineNumber":125,"author":{"gitId":"cjaycee"},"content":"","lastModifiedDate":"2025-08-22T02:02:56","isFullCredit":false},{"lineNumber":126,"author":{"gitId":"cjaycee"},"content":"        Event(String description, String from, String to) {","lastModifiedDate":"2025-08-22T02:02:56","isFullCredit":false},{"lineNumber":127,"author":{"gitId":"cjaycee"},"content":"            super(description);","lastModifiedDate":"2025-08-22T02:02:56","isFullCredit":false},{"lineNumber":128,"author":{"gitId":"cjaycee"},"content":"            this.from \u003d from;","lastModifiedDate":"2025-08-22T02:02:56","isFullCredit":false},{"lineNumber":129,"author":{"gitId":"cjaycee"},"content":"            this.to \u003d to;","lastModifiedDate":"2025-08-22T02:02:56","isFullCredit":false},{"lineNumber":130,"author":{"gitId":"cjaycee"},"content":"        }","lastModifiedDate":"2025-08-22T02:02:56","isFullCredit":false},{"lineNumber":131,"author":{"gitId":"cjaycee"},"content":"","lastModifiedDate":"2025-08-22T02:02:56","isFullCredit":false},{"lineNumber":132,"author":{"gitId":"cjaycee"},"content":"        @Override","lastModifiedDate":"2025-08-22T02:02:56","isFullCredit":false},{"lineNumber":133,"author":{"gitId":"cjaycee"},"content":"        String getTaskType() {","lastModifiedDate":"2025-08-22T02:02:56","isFullCredit":false},{"lineNumber":134,"author":{"gitId":"cjaycee"},"content":"            return \"[E]\";","lastModifiedDate":"2025-08-22T02:02:56","isFullCredit":false},{"lineNumber":135,"author":{"gitId":"cjaycee"},"content":"        }","lastModifiedDate":"2025-08-22T02:02:56","isFullCredit":false},{"lineNumber":136,"author":{"gitId":"cjaycee"},"content":"","lastModifiedDate":"2025-08-22T02:02:56","isFullCredit":false},{"lineNumber":137,"author":{"gitId":"cjaycee"},"content":"        @Override","lastModifiedDate":"2025-08-22T02:02:56","isFullCredit":false},{"lineNumber":138,"author":{"gitId":"cjaycee"},"content":"        String getFullDescription() {","lastModifiedDate":"2025-08-22T02:02:56","isFullCredit":false},{"lineNumber":139,"author":{"gitId":"cjaycee"},"content":"            return getTaskType() + super.toString() + \" (from: \" + from + \" to: \" + to + \")\";","lastModifiedDate":"2025-08-22T02:02:56","isFullCredit":false},{"lineNumber":140,"author":{"gitId":"cjaycee"},"content":"        }","lastModifiedDate":"2025-08-22T02:02:56","isFullCredit":false},{"lineNumber":141,"author":{"gitId":"cjaycee"},"content":"","lastModifiedDate":"2025-08-22T02:02:56","isFullCredit":false},{"lineNumber":142,"author":{"gitId":"cjaycee"},"content":"        @Override","lastModifiedDate":"2025-08-22T02:02:56","isFullCredit":false},{"lineNumber":143,"author":{"gitId":"cjaycee"},"content":"        public String toString() {","lastModifiedDate":"2025-08-22T02:02:56","isFullCredit":false},{"lineNumber":144,"author":{"gitId":"cjaycee"},"content":"            return getFullDescription();","lastModifiedDate":"2025-08-22T02:02:56","isFullCredit":false},{"lineNumber":145,"author":{"gitId":"cjaycee"},"content":"        }","lastModifiedDate":"2025-08-22T02:02:56","isFullCredit":false},{"lineNumber":146,"author":{"gitId":"cjaycee"},"content":"    }","lastModifiedDate":"2025-08-22T01:18:02","isFullCredit":false},{"lineNumber":147,"author":{"gitId":"cjaycee"},"content":"","lastModifiedDate":"2025-08-22T01:18:02","isFullCredit":false},{"lineNumber":148,"author":{"gitId":"cjaycee"},"content":"    public static void main(String[] args) {","lastModifiedDate":"2025-08-22T00:25:30","isFullCredit":false},{"lineNumber":149,"author":{"gitId":"cjaycee"},"content":"        ArrayList\u003cTask\u003e tasks \u003d new ArrayList\u003c\u003e();","lastModifiedDate":"2025-08-22T01:18:02","isFullCredit":false},{"lineNumber":150,"author":{"gitId":"cjaycee"},"content":"        Scanner scanner \u003d new Scanner(System.in);","lastModifiedDate":"2025-08-22T00:53:41","isFullCredit":false},{"lineNumber":151,"author":{"gitId":"cjaycee"},"content":"","lastModifiedDate":"2025-08-22T00:53:41","isFullCredit":false},{"lineNumber":152,"author":{"gitId":"cjaycee"},"content":"        printLine();","lastModifiedDate":"2025-08-28T16:59:27","isFullCredit":false},{"lineNumber":153,"author":{"gitId":"cjaycee"},"content":"        System.out.println(\"Hello! I\u0027m Usagi, your friendly task manager!\");","lastModifiedDate":"2025-08-22T02:07:02","isFullCredit":false},{"lineNumber":154,"author":{"gitId":"cjaycee"},"content":"        System.out.println(\"What can I do for you?\");","lastModifiedDate":"2025-08-22T00:37:57","isFullCredit":false},{"lineNumber":155,"author":{"gitId":"cjaycee"},"content":"        printLine();","lastModifiedDate":"2025-08-28T16:59:27","isFullCredit":false},{"lineNumber":156,"author":{"gitId":"cjaycee"},"content":"","lastModifiedDate":"2025-08-28T16:59:27","isFullCredit":false},{"lineNumber":157,"author":{"gitId":"cjaycee"},"content":"        boolean isRunning \u003d true;","lastModifiedDate":"2025-08-28T16:59:27","isFullCredit":false},{"lineNumber":158,"author":{"gitId":"cjaycee"},"content":"","lastModifiedDate":"2025-08-22T00:37:57","isFullCredit":false},{"lineNumber":159,"author":{"gitId":"cjaycee"},"content":"        while (isRunning \u0026\u0026 scanner.hasNextLine()) {","lastModifiedDate":"2025-08-28T16:59:27","isFullCredit":false},{"lineNumber":160,"author":{"gitId":"cjaycee"},"content":"            try {","lastModifiedDate":"2025-08-22T02:07:02","isFullCredit":false},{"lineNumber":161,"author":{"gitId":"cjaycee"},"content":"                String input \u003d scanner.nextLine().trim();","lastModifiedDate":"2025-08-28T16:59:27","isFullCredit":false},{"lineNumber":162,"author":{"gitId":"cjaycee"},"content":"","lastModifiedDate":"2025-08-22T00:37:57","isFullCredit":false},{"lineNumber":163,"author":{"gitId":"cjaycee"},"content":"                if (input.equalsIgnoreCase(\"bye\")) {","lastModifiedDate":"2025-08-22T00:37:57","isFullCredit":false},{"lineNumber":164,"author":{"gitId":"cjaycee"},"content":"                    isRunning \u003d false;","lastModifiedDate":"2025-08-28T16:59:27","isFullCredit":false},{"lineNumber":165,"author":{"gitId":"cjaycee"},"content":"                } else if (input.equalsIgnoreCase(\"list\")) {","lastModifiedDate":"2025-08-22T00:53:41","isFullCredit":false},{"lineNumber":166,"author":{"gitId":"cjaycee"},"content":"                    displayTaskList(tasks);","lastModifiedDate":"2025-08-22T01:18:02","isFullCredit":false},{"lineNumber":167,"author":{"gitId":"cjaycee"},"content":"                } else if (input.startsWith(\"mark \")) {","lastModifiedDate":"2025-08-22T01:18:02","isFullCredit":false},{"lineNumber":168,"author":{"gitId":"cjaycee"},"content":"                    handleMarkCommand(tasks, input, true);","lastModifiedDate":"2025-08-22T02:07:02","isFullCredit":false},{"lineNumber":169,"author":{"gitId":"cjaycee"},"content":"                } else if (input.startsWith(\"unmark \")) {","lastModifiedDate":"2025-08-22T01:18:02","isFullCredit":false},{"lineNumber":170,"author":{"gitId":"cjaycee"},"content":"                    handleMarkCommand(tasks, input, false);","lastModifiedDate":"2025-08-22T02:07:02","isFullCredit":false},{"lineNumber":171,"author":{"gitId":"cjaycee"},"content":"                } else if (input.startsWith(\"todo \")) {","lastModifiedDate":"2025-08-22T02:02:56","isFullCredit":false},{"lineNumber":172,"author":{"gitId":"cjaycee"},"content":"                    addTodoTask(tasks, input);","lastModifiedDate":"2025-08-22T02:02:56","isFullCredit":false},{"lineNumber":173,"author":{"gitId":"cjaycee"},"content":"                } else if (input.startsWith(\"deadline \")) {","lastModifiedDate":"2025-08-22T02:02:56","isFullCredit":false},{"lineNumber":174,"author":{"gitId":"cjaycee"},"content":"                    addDeadlineTask(tasks, input);","lastModifiedDate":"2025-08-22T02:02:56","isFullCredit":false},{"lineNumber":175,"author":{"gitId":"cjaycee"},"content":"                } else if (input.startsWith(\"event \")) {","lastModifiedDate":"2025-08-22T02:02:56","isFullCredit":false},{"lineNumber":176,"author":{"gitId":"cjaycee"},"content":"                    addEventTask(tasks, input);","lastModifiedDate":"2025-08-22T02:02:56","isFullCredit":false},{"lineNumber":177,"author":{"gitId":"cjaycee"},"content":"                } else if (input.startsWith(\"delete \")) {","lastModifiedDate":"2025-08-28T16:59:27","isFullCredit":false},{"lineNumber":178,"author":{"gitId":"cjaycee"},"content":"                    deleteTask(tasks, input);","lastModifiedDate":"2025-08-28T16:59:27","isFullCredit":false},{"lineNumber":179,"author":{"gitId":"cjaycee"},"content":"                } else if (!input.isEmpty()) {","lastModifiedDate":"2025-08-22T01:18:02","isFullCredit":false},{"lineNumber":180,"author":{"gitId":"cjaycee"},"content":"                    throw new InvalidCommandException();","lastModifiedDate":"2025-08-22T02:07:02","isFullCredit":false},{"lineNumber":181,"author":{"gitId":"cjaycee"},"content":"                }","lastModifiedDate":"2025-08-22T02:07:02","isFullCredit":false},{"lineNumber":182,"author":{"gitId":"cjaycee"},"content":"            } catch (UsagiException e) {","lastModifiedDate":"2025-08-22T02:07:02","isFullCredit":false},{"lineNumber":183,"author":{"gitId":"cjaycee"},"content":"                printErrorMessage(e.getMessage());","lastModifiedDate":"2025-08-22T02:07:02","isFullCredit":false},{"lineNumber":184,"author":{"gitId":"cjaycee"},"content":"            } catch (NoSuchElementException e) {","lastModifiedDate":"2025-08-28T16:59:27","isFullCredit":false},{"lineNumber":185,"author":{"gitId":"cjaycee"},"content":"                // Handle end of input gracefully","lastModifiedDate":"2025-08-28T16:59:27","isFullCredit":false},{"lineNumber":186,"author":{"gitId":"cjaycee"},"content":"                isRunning \u003d false;","lastModifiedDate":"2025-08-28T16:59:27","isFullCredit":false},{"lineNumber":187,"author":{"gitId":"cjaycee"},"content":"            }","lastModifiedDate":"2025-08-22T01:18:02","isFullCredit":false},{"lineNumber":188,"author":{"gitId":"cjaycee"},"content":"        }","lastModifiedDate":"2025-08-22T01:18:02","isFullCredit":false},{"lineNumber":189,"author":{"gitId":"cjaycee"},"content":"","lastModifiedDate":"2025-08-22T01:18:02","isFullCredit":false},{"lineNumber":190,"author":{"gitId":"cjaycee"},"content":"        printLine();","lastModifiedDate":"2025-08-28T16:59:27","isFullCredit":false},{"lineNumber":191,"author":{"gitId":"cjaycee"},"content":"        System.out.println(\"Bye. Hope to see you again soon!\");","lastModifiedDate":"2025-08-22T01:18:02","isFullCredit":false},{"lineNumber":192,"author":{"gitId":"cjaycee"},"content":"        printLine();","lastModifiedDate":"2025-08-28T16:59:27","isFullCredit":false},{"lineNumber":193,"author":{"gitId":"cjaycee"},"content":"        scanner.close();","lastModifiedDate":"2025-08-22T01:18:02","isFullCredit":false},{"lineNumber":194,"author":{"gitId":"cjaycee"},"content":"    }","lastModifiedDate":"2025-08-22T01:18:02","isFullCredit":false},{"lineNumber":195,"author":{"gitId":"cjaycee"},"content":"","lastModifiedDate":"2025-08-22T01:18:02","isFullCredit":false},{"lineNumber":196,"author":{"gitId":"cjaycee"},"content":"    private static void printErrorMessage(String message) {","lastModifiedDate":"2025-08-22T02:07:02","isFullCredit":false},{"lineNumber":197,"author":{"gitId":"cjaycee"},"content":"        printLine();","lastModifiedDate":"2025-08-28T16:59:27","isFullCredit":false},{"lineNumber":198,"author":{"gitId":"cjaycee"},"content":"        System.out.println(\"Oops! \" + message);","lastModifiedDate":"2025-08-22T02:07:02","isFullCredit":false},{"lineNumber":199,"author":{"gitId":"cjaycee"},"content":"        printLine();","lastModifiedDate":"2025-08-28T16:59:27","isFullCredit":false},{"lineNumber":200,"author":{"gitId":"cjaycee"},"content":"    }","lastModifiedDate":"2025-08-22T02:07:02","isFullCredit":false},{"lineNumber":201,"author":{"gitId":"cjaycee"},"content":"","lastModifiedDate":"2025-08-22T02:07:02","isFullCredit":false},{"lineNumber":202,"author":{"gitId":"cjaycee"},"content":"    private static void displayTaskList(ArrayList\u003cTask\u003e tasks) {","lastModifiedDate":"2025-08-22T01:18:02","isFullCredit":false},{"lineNumber":203,"author":{"gitId":"cjaycee"},"content":"        printLine();","lastModifiedDate":"2025-08-28T16:59:27","isFullCredit":false},{"lineNumber":204,"author":{"gitId":"cjaycee"},"content":"        if (tasks.isEmpty()) {","lastModifiedDate":"2025-08-22T00:53:41","isFullCredit":false},{"lineNumber":205,"author":{"gitId":"cjaycee"},"content":"            System.out.println(\"Your list is empty! Add some tasks first.\");","lastModifiedDate":"2025-08-22T00:53:41","isFullCredit":false},{"lineNumber":206,"author":{"gitId":"cjaycee"},"content":"        } else {","lastModifiedDate":"2025-08-22T00:53:41","isFullCredit":false},{"lineNumber":207,"author":{"gitId":"cjaycee"},"content":"            System.out.println(\"Here are the tasks in your list:\");","lastModifiedDate":"2025-08-22T01:18:02","isFullCredit":false},{"lineNumber":208,"author":{"gitId":"cjaycee"},"content":"            for (int i \u003d 0; i \u003c tasks.size(); i++) {","lastModifiedDate":"2025-08-22T00:53:41","isFullCredit":false},{"lineNumber":209,"author":{"gitId":"cjaycee"},"content":"                System.out.println((i + 1) + \".\" + tasks.get(i).toString());","lastModifiedDate":"2025-08-22T01:18:02","isFullCredit":false},{"lineNumber":210,"author":{"gitId":"cjaycee"},"content":"            }","lastModifiedDate":"2025-08-22T00:53:41","isFullCredit":false},{"lineNumber":211,"author":{"gitId":"cjaycee"},"content":"        }","lastModifiedDate":"2025-08-22T00:53:41","isFullCredit":false},{"lineNumber":212,"author":{"gitId":"cjaycee"},"content":"        printLine();","lastModifiedDate":"2025-08-28T16:59:27","isFullCredit":false},{"lineNumber":213,"author":{"gitId":"cjaycee"},"content":"    }","lastModifiedDate":"2025-08-22T01:18:02","isFullCredit":false},{"lineNumber":214,"author":{"gitId":"cjaycee"},"content":"","lastModifiedDate":"2025-08-22T01:18:02","isFullCredit":false},{"lineNumber":215,"author":{"gitId":"cjaycee"},"content":"    private static void addTodoTask(ArrayList\u003cTask\u003e tasks, String input) throws UsagiException {","lastModifiedDate":"2025-08-22T02:07:02","isFullCredit":false},{"lineNumber":216,"author":{"gitId":"cjaycee"},"content":"        String description \u003d input.substring(5).trim();","lastModifiedDate":"2025-08-22T02:02:56","isFullCredit":false},{"lineNumber":217,"author":{"gitId":"cjaycee"},"content":"        if (description.isEmpty()) {","lastModifiedDate":"2025-08-22T02:02:56","isFullCredit":false},{"lineNumber":218,"author":{"gitId":"cjaycee"},"content":"            throw new EmptyDescriptionException(\"todo\");","lastModifiedDate":"2025-08-22T02:07:02","isFullCredit":false},{"lineNumber":219,"author":{"gitId":"cjaycee"},"content":"        }","lastModifiedDate":"2025-08-22T02:02:56","isFullCredit":false},{"lineNumber":220,"author":{"gitId":"cjaycee"},"content":"","lastModifiedDate":"2025-08-22T02:02:56","isFullCredit":false},{"lineNumber":221,"author":{"gitId":"cjaycee"},"content":"        Task newTask \u003d new Todo(description);","lastModifiedDate":"2025-08-22T02:02:56","isFullCredit":false},{"lineNumber":222,"author":{"gitId":"cjaycee"},"content":"        tasks.add(newTask);","lastModifiedDate":"2025-08-22T02:02:56","isFullCredit":false},{"lineNumber":223,"author":{"gitId":"cjaycee"},"content":"        printLine();","lastModifiedDate":"2025-08-28T16:59:27","isFullCredit":false},{"lineNumber":224,"author":{"gitId":"cjaycee"},"content":"        System.out.println(\"Got it. I\u0027ve added this task:\");","lastModifiedDate":"2025-08-22T02:02:56","isFullCredit":false},{"lineNumber":225,"author":{"gitId":"cjaycee"},"content":"        System.out.println(\"  \" + newTask.toString());","lastModifiedDate":"2025-08-22T02:02:56","isFullCredit":false},{"lineNumber":226,"author":{"gitId":"cjaycee"},"content":"        System.out.println(\"Now you have \" + tasks.size() + \" tasks in the list.\");","lastModifiedDate":"2025-08-22T02:02:56","isFullCredit":false},{"lineNumber":227,"author":{"gitId":"cjaycee"},"content":"        printLine();","lastModifiedDate":"2025-08-28T16:59:27","isFullCredit":false},{"lineNumber":228,"author":{"gitId":"cjaycee"},"content":"    }","lastModifiedDate":"2025-08-22T02:02:56","isFullCredit":false},{"lineNumber":229,"author":{"gitId":"cjaycee"},"content":"","lastModifiedDate":"2025-08-22T02:02:56","isFullCredit":false},{"lineNumber":230,"author":{"gitId":"cjaycee"},"content":"    private static void addDeadlineTask(ArrayList\u003cTask\u003e tasks, String input) throws UsagiException {","lastModifiedDate":"2025-08-22T02:07:02","isFullCredit":false},{"lineNumber":231,"author":{"gitId":"cjaycee"},"content":"        String withoutPrefix \u003d input.substring(9).trim();","lastModifiedDate":"2025-08-22T02:02:56","isFullCredit":false},{"lineNumber":232,"author":{"gitId":"cjaycee"},"content":"        if (withoutPrefix.isEmpty()) {","lastModifiedDate":"2025-08-22T02:07:02","isFullCredit":false},{"lineNumber":233,"author":{"gitId":"cjaycee"},"content":"            throw new EmptyDescriptionException(\"deadline\");","lastModifiedDate":"2025-08-22T02:07:02","isFullCredit":false},{"lineNumber":234,"author":{"gitId":"cjaycee"},"content":"        }","lastModifiedDate":"2025-08-22T02:07:02","isFullCredit":false},{"lineNumber":235,"author":{"gitId":"cjaycee"},"content":"","lastModifiedDate":"2025-08-22T02:07:02","isFullCredit":false},{"lineNumber":236,"author":{"gitId":"cjaycee"},"content":"        String[] parts \u003d withoutPrefix.split(\"/by\", 2);","lastModifiedDate":"2025-08-22T02:02:56","isFullCredit":false},{"lineNumber":237,"author":{"gitId":"cjaycee"},"content":"","lastModifiedDate":"2025-08-22T02:02:56","isFullCredit":false},{"lineNumber":238,"author":{"gitId":"cjaycee"},"content":"        if (parts.length \u003c 2) {","lastModifiedDate":"2025-08-22T02:02:56","isFullCredit":false},{"lineNumber":239,"author":{"gitId":"cjaycee"},"content":"            throw new InvalidFormatException(\"deadline \u003cdescription\u003e /by \u003ctime\u003e\");","lastModifiedDate":"2025-08-22T02:07:02","isFullCredit":false},{"lineNumber":240,"author":{"gitId":"cjaycee"},"content":"        }","lastModifiedDate":"2025-08-22T02:02:56","isFullCredit":false},{"lineNumber":241,"author":{"gitId":"cjaycee"},"content":"","lastModifiedDate":"2025-08-22T02:02:56","isFullCredit":false},{"lineNumber":242,"author":{"gitId":"cjaycee"},"content":"        String description \u003d parts[0].trim();","lastModifiedDate":"2025-08-22T02:02:56","isFullCredit":false},{"lineNumber":243,"author":{"gitId":"cjaycee"},"content":"        String by \u003d parts[1].trim();","lastModifiedDate":"2025-08-22T02:02:56","isFullCredit":false},{"lineNumber":244,"author":{"gitId":"cjaycee"},"content":"","lastModifiedDate":"2025-08-22T02:02:56","isFullCredit":false},{"lineNumber":245,"author":{"gitId":"cjaycee"},"content":"        if (description.isEmpty()) {","lastModifiedDate":"2025-08-22T02:07:02","isFullCredit":false},{"lineNumber":246,"author":{"gitId":"cjaycee"},"content":"            throw new EmptyDescriptionException(\"deadline\");","lastModifiedDate":"2025-08-22T02:07:02","isFullCredit":false},{"lineNumber":247,"author":{"gitId":"cjaycee"},"content":"        }","lastModifiedDate":"2025-08-22T02:07:02","isFullCredit":false},{"lineNumber":248,"author":{"gitId":"cjaycee"},"content":"        if (by.isEmpty()) {","lastModifiedDate":"2025-08-22T02:07:02","isFullCredit":false},{"lineNumber":249,"author":{"gitId":"cjaycee"},"content":"            throw new InvalidFormatException(\"deadline \u003cdescription\u003e /by \u003ctime\u003e (time cannot be empty)\");","lastModifiedDate":"2025-08-22T02:07:02","isFullCredit":false},{"lineNumber":250,"author":{"gitId":"cjaycee"},"content":"        }","lastModifiedDate":"2025-08-22T02:02:56","isFullCredit":false},{"lineNumber":251,"author":{"gitId":"cjaycee"},"content":"","lastModifiedDate":"2025-08-22T02:02:56","isFullCredit":false},{"lineNumber":252,"author":{"gitId":"cjaycee"},"content":"        Task newTask \u003d new Deadline(description, by);","lastModifiedDate":"2025-08-22T02:02:56","isFullCredit":false},{"lineNumber":253,"author":{"gitId":"cjaycee"},"content":"        tasks.add(newTask);","lastModifiedDate":"2025-08-22T02:02:56","isFullCredit":false},{"lineNumber":254,"author":{"gitId":"cjaycee"},"content":"        printLine();","lastModifiedDate":"2025-08-28T16:59:27","isFullCredit":false},{"lineNumber":255,"author":{"gitId":"cjaycee"},"content":"        System.out.println(\"Got it. I\u0027ve added this task:\");","lastModifiedDate":"2025-08-22T02:02:56","isFullCredit":false},{"lineNumber":256,"author":{"gitId":"cjaycee"},"content":"        System.out.println(\"  \" + newTask.toString());","lastModifiedDate":"2025-08-22T02:02:56","isFullCredit":false},{"lineNumber":257,"author":{"gitId":"cjaycee"},"content":"        System.out.println(\"Now you have \" + tasks.size() + \" tasks in the list.\");","lastModifiedDate":"2025-08-22T02:02:56","isFullCredit":false},{"lineNumber":258,"author":{"gitId":"cjaycee"},"content":"        printLine();","lastModifiedDate":"2025-08-28T16:59:27","isFullCredit":false},{"lineNumber":259,"author":{"gitId":"cjaycee"},"content":"    }","lastModifiedDate":"2025-08-22T02:02:56","isFullCredit":false},{"lineNumber":260,"author":{"gitId":"cjaycee"},"content":"","lastModifiedDate":"2025-08-22T02:02:56","isFullCredit":false},{"lineNumber":261,"author":{"gitId":"cjaycee"},"content":"    private static void addEventTask(ArrayList\u003cTask\u003e tasks, String input) throws UsagiException {","lastModifiedDate":"2025-08-22T02:07:02","isFullCredit":false},{"lineNumber":262,"author":{"gitId":"cjaycee"},"content":"        String withoutPrefix \u003d input.substring(6).trim();","lastModifiedDate":"2025-08-22T02:02:56","isFullCredit":false},{"lineNumber":263,"author":{"gitId":"cjaycee"},"content":"        if (withoutPrefix.isEmpty()) {","lastModifiedDate":"2025-08-22T02:07:02","isFullCredit":false},{"lineNumber":264,"author":{"gitId":"cjaycee"},"content":"            throw new EmptyDescriptionException(\"event\");","lastModifiedDate":"2025-08-22T02:07:02","isFullCredit":false},{"lineNumber":265,"author":{"gitId":"cjaycee"},"content":"        }","lastModifiedDate":"2025-08-22T02:07:02","isFullCredit":false},{"lineNumber":266,"author":{"gitId":"cjaycee"},"content":"","lastModifiedDate":"2025-08-22T02:07:02","isFullCredit":false},{"lineNumber":267,"author":{"gitId":"cjaycee"},"content":"        String[] parts \u003d withoutPrefix.split(\"/from\", 2);","lastModifiedDate":"2025-08-22T02:02:56","isFullCredit":false},{"lineNumber":268,"author":{"gitId":"cjaycee"},"content":"","lastModifiedDate":"2025-08-22T02:02:56","isFullCredit":false},{"lineNumber":269,"author":{"gitId":"cjaycee"},"content":"        if (parts.length \u003c 2) {","lastModifiedDate":"2025-08-22T02:02:56","isFullCredit":false},{"lineNumber":270,"author":{"gitId":"cjaycee"},"content":"            throw new InvalidFormatException(\"event \u003cdescription\u003e /from \u003cstart\u003e /to \u003cend\u003e\");","lastModifiedDate":"2025-08-22T02:07:02","isFullCredit":false},{"lineNumber":271,"author":{"gitId":"cjaycee"},"content":"        }","lastModifiedDate":"2025-08-22T02:02:56","isFullCredit":false},{"lineNumber":272,"author":{"gitId":"cjaycee"},"content":"","lastModifiedDate":"2025-08-22T02:02:56","isFullCredit":false},{"lineNumber":273,"author":{"gitId":"cjaycee"},"content":"        String description \u003d parts[0].trim();","lastModifiedDate":"2025-08-22T02:02:56","isFullCredit":false},{"lineNumber":274,"author":{"gitId":"cjaycee"},"content":"        String[] timeParts \u003d parts[1].split(\"/to\", 2);","lastModifiedDate":"2025-08-22T02:02:56","isFullCredit":false},{"lineNumber":275,"author":{"gitId":"cjaycee"},"content":"","lastModifiedDate":"2025-08-22T02:02:56","isFullCredit":false},{"lineNumber":276,"author":{"gitId":"cjaycee"},"content":"        if (timeParts.length \u003c 2) {","lastModifiedDate":"2025-08-22T02:02:56","isFullCredit":false},{"lineNumber":277,"author":{"gitId":"cjaycee"},"content":"            throw new InvalidFormatException(\"event \u003cdescription\u003e /from \u003cstart\u003e /to \u003cend\u003e\");","lastModifiedDate":"2025-08-22T02:07:02","isFullCredit":false},{"lineNumber":278,"author":{"gitId":"cjaycee"},"content":"        }","lastModifiedDate":"2025-08-22T02:02:56","isFullCredit":false},{"lineNumber":279,"author":{"gitId":"cjaycee"},"content":"","lastModifiedDate":"2025-08-22T02:02:56","isFullCredit":false},{"lineNumber":280,"author":{"gitId":"cjaycee"},"content":"        String from \u003d timeParts[0].trim();","lastModifiedDate":"2025-08-22T02:02:56","isFullCredit":false},{"lineNumber":281,"author":{"gitId":"cjaycee"},"content":"        String to \u003d timeParts[1].trim();","lastModifiedDate":"2025-08-22T02:02:56","isFullCredit":false},{"lineNumber":282,"author":{"gitId":"cjaycee"},"content":"","lastModifiedDate":"2025-08-22T02:02:56","isFullCredit":false},{"lineNumber":283,"author":{"gitId":"cjaycee"},"content":"        if (description.isEmpty()) {","lastModifiedDate":"2025-08-22T02:07:02","isFullCredit":false},{"lineNumber":284,"author":{"gitId":"cjaycee"},"content":"            throw new EmptyDescriptionException(\"event\");","lastModifiedDate":"2025-08-22T02:07:02","isFullCredit":false},{"lineNumber":285,"author":{"gitId":"cjaycee"},"content":"        }","lastModifiedDate":"2025-08-22T02:07:02","isFullCredit":false},{"lineNumber":286,"author":{"gitId":"cjaycee"},"content":"        if (from.isEmpty() || to.isEmpty()) {","lastModifiedDate":"2025-08-22T02:07:02","isFullCredit":false},{"lineNumber":287,"author":{"gitId":"cjaycee"},"content":"            throw new InvalidFormatException(\"event \u003cdescription\u003e /from \u003cstart\u003e /to \u003cend\u003e (times cannot be empty)\");","lastModifiedDate":"2025-08-22T02:07:02","isFullCredit":false},{"lineNumber":288,"author":{"gitId":"cjaycee"},"content":"        }","lastModifiedDate":"2025-08-22T02:02:56","isFullCredit":false},{"lineNumber":289,"author":{"gitId":"cjaycee"},"content":"","lastModifiedDate":"2025-08-22T02:02:56","isFullCredit":false},{"lineNumber":290,"author":{"gitId":"cjaycee"},"content":"        Task newTask \u003d new Event(description, from, to);","lastModifiedDate":"2025-08-22T02:02:56","isFullCredit":false},{"lineNumber":291,"author":{"gitId":"cjaycee"},"content":"        tasks.add(newTask);","lastModifiedDate":"2025-08-22T01:18:02","isFullCredit":false},{"lineNumber":292,"author":{"gitId":"cjaycee"},"content":"        printLine();","lastModifiedDate":"2025-08-28T16:59:27","isFullCredit":false},{"lineNumber":293,"author":{"gitId":"cjaycee"},"content":"        System.out.println(\"Got it. I\u0027ve added this task:\");","lastModifiedDate":"2025-08-22T02:02:56","isFullCredit":false},{"lineNumber":294,"author":{"gitId":"cjaycee"},"content":"        System.out.println(\"  \" + newTask.toString());","lastModifiedDate":"2025-08-22T02:02:56","isFullCredit":false},{"lineNumber":295,"author":{"gitId":"cjaycee"},"content":"        System.out.println(\"Now you have \" + tasks.size() + \" tasks in the list.\");","lastModifiedDate":"2025-08-22T02:02:56","isFullCredit":false},{"lineNumber":296,"author":{"gitId":"cjaycee"},"content":"        printLine();","lastModifiedDate":"2025-08-28T16:59:27","isFullCredit":false},{"lineNumber":297,"author":{"gitId":"cjaycee"},"content":"    }","lastModifiedDate":"2025-08-22T00:37:57","isFullCredit":false},{"lineNumber":298,"author":{"gitId":"cjaycee"},"content":"","lastModifiedDate":"2025-08-22T00:37:57","isFullCredit":false},{"lineNumber":299,"author":{"gitId":"cjaycee"},"content":"    private static void handleMarkCommand(ArrayList\u003cTask\u003e tasks, String input, boolean markAsDone) throws UsagiException {","lastModifiedDate":"2025-08-22T02:07:02","isFullCredit":false},{"lineNumber":300,"author":{"gitId":"cjaycee"},"content":"        try {","lastModifiedDate":"2025-08-22T01:18:02","isFullCredit":false},{"lineNumber":301,"author":{"gitId":"cjaycee"},"content":"            String[] parts \u003d input.split(\" \", 2);","lastModifiedDate":"2025-08-22T02:07:02","isFullCredit":false},{"lineNumber":302,"author":{"gitId":"cjaycee"},"content":"            if (parts.length \u003c 2) {","lastModifiedDate":"2025-08-22T02:07:02","isFullCredit":false},{"lineNumber":303,"author":{"gitId":"cjaycee"},"content":"                throw new InvalidFormatException((markAsDone ? \"mark\" : \"unmark\") + \" \u003ctask-number\u003e\");","lastModifiedDate":"2025-08-22T02:07:02","isFullCredit":false},{"lineNumber":304,"author":{"gitId":"cjaycee"},"content":"            }","lastModifiedDate":"2025-08-22T02:07:02","isFullCredit":false},{"lineNumber":305,"author":{"gitId":"cjaycee"},"content":"","lastModifiedDate":"2025-08-22T02:07:02","isFullCredit":false},{"lineNumber":306,"author":{"gitId":"cjaycee"},"content":"            int taskNumber \u003d Integer.parseInt(parts[1]) - 1;","lastModifiedDate":"2025-08-22T02:07:02","isFullCredit":false},{"lineNumber":307,"author":{"gitId":"cjaycee"},"content":"","lastModifiedDate":"2025-08-22T02:07:02","isFullCredit":false},{"lineNumber":308,"author":{"gitId":"cjaycee"},"content":"            if (taskNumber \u003c 0 || taskNumber \u003e\u003d tasks.size()) {","lastModifiedDate":"2025-08-22T02:07:02","isFullCredit":false},{"lineNumber":309,"author":{"gitId":"cjaycee"},"content":"                throw new InvalidTaskNumberException(tasks.size());","lastModifiedDate":"2025-08-22T02:07:02","isFullCredit":false},{"lineNumber":310,"author":{"gitId":"cjaycee"},"content":"            }","lastModifiedDate":"2025-08-22T02:07:02","isFullCredit":false},{"lineNumber":311,"author":{"gitId":"cjaycee"},"content":"","lastModifiedDate":"2025-08-22T01:18:02","isFullCredit":false},{"lineNumber":312,"author":{"gitId":"cjaycee"},"content":"            Task task \u003d tasks.get(taskNumber);","lastModifiedDate":"2025-08-22T01:18:02","isFullCredit":false},{"lineNumber":313,"author":{"gitId":"cjaycee"},"content":"","lastModifiedDate":"2025-08-22T01:18:02","isFullCredit":false},{"lineNumber":314,"author":{"gitId":"cjaycee"},"content":"            if (markAsDone) {","lastModifiedDate":"2025-08-22T01:18:02","isFullCredit":false},{"lineNumber":315,"author":{"gitId":"cjaycee"},"content":"                task.markAsDone();","lastModifiedDate":"2025-08-22T01:18:02","isFullCredit":false},{"lineNumber":316,"author":{"gitId":"cjaycee"},"content":"                printLine();","lastModifiedDate":"2025-08-28T16:59:27","isFullCredit":false},{"lineNumber":317,"author":{"gitId":"cjaycee"},"content":"                System.out.println(\"Nice! I\u0027ve marked this task as done:\");","lastModifiedDate":"2025-08-22T01:18:02","isFullCredit":false},{"lineNumber":318,"author":{"gitId":"cjaycee"},"content":"                System.out.println(\"  \" + task.toString());","lastModifiedDate":"2025-08-22T01:18:02","isFullCredit":false},{"lineNumber":319,"author":{"gitId":"cjaycee"},"content":"                printLine();","lastModifiedDate":"2025-08-28T16:59:27","isFullCredit":false},{"lineNumber":320,"author":{"gitId":"cjaycee"},"content":"            } else {","lastModifiedDate":"2025-08-22T01:18:02","isFullCredit":false},{"lineNumber":321,"author":{"gitId":"cjaycee"},"content":"                task.markAsNotDone();","lastModifiedDate":"2025-08-22T01:18:02","isFullCredit":false},{"lineNumber":322,"author":{"gitId":"cjaycee"},"content":"                printLine();","lastModifiedDate":"2025-08-28T16:59:27","isFullCredit":false},{"lineNumber":323,"author":{"gitId":"cjaycee"},"content":"                System.out.println(\"OK, I\u0027ve marked this task as not done yet:\");","lastModifiedDate":"2025-08-22T01:18:02","isFullCredit":false},{"lineNumber":324,"author":{"gitId":"cjaycee"},"content":"                System.out.println(\"  \" + task.toString());","lastModifiedDate":"2025-08-22T01:18:02","isFullCredit":false},{"lineNumber":325,"author":{"gitId":"cjaycee"},"content":"                printLine();","lastModifiedDate":"2025-08-28T16:59:27","isFullCredit":false},{"lineNumber":326,"author":{"gitId":"cjaycee"},"content":"            }","lastModifiedDate":"2025-08-22T01:18:02","isFullCredit":false},{"lineNumber":327,"author":{"gitId":"cjaycee"},"content":"        } catch (NumberFormatException e) {","lastModifiedDate":"2025-08-22T02:07:02","isFullCredit":false},{"lineNumber":328,"author":{"gitId":"cjaycee"},"content":"            throw new InvalidFormatException((markAsDone ? \"mark\" : \"unmark\") + \" \u003ctask-number\u003e (must be a number)\");","lastModifiedDate":"2025-08-22T02:07:02","isFullCredit":false},{"lineNumber":329,"author":{"gitId":"cjaycee"},"content":"        }","lastModifiedDate":"2025-08-22T01:18:02","isFullCredit":false},{"lineNumber":330,"author":{"gitId":"cjaycee"},"content":"    }","lastModifiedDate":"2025-08-22T00:25:30","isFullCredit":false},{"lineNumber":331,"author":{"gitId":"cjaycee"},"content":"","lastModifiedDate":"2025-08-28T16:59:27","isFullCredit":false},{"lineNumber":332,"author":{"gitId":"cjaycee"},"content":"    private static void deleteTask(ArrayList\u003cTask\u003e tasks, String input) throws UsagiException {","lastModifiedDate":"2025-08-28T16:59:27","isFullCredit":false},{"lineNumber":333,"author":{"gitId":"cjaycee"},"content":"        try {","lastModifiedDate":"2025-08-28T16:59:27","isFullCredit":false},{"lineNumber":334,"author":{"gitId":"cjaycee"},"content":"            String[] parts \u003d input.split(\" \", 2);","lastModifiedDate":"2025-08-28T16:59:27","isFullCredit":false},{"lineNumber":335,"author":{"gitId":"cjaycee"},"content":"            if (parts.length \u003c 2) {","lastModifiedDate":"2025-08-28T16:59:27","isFullCredit":false},{"lineNumber":336,"author":{"gitId":"cjaycee"},"content":"                throw new InvalidFormatException(\"delete \u003ctask-number\u003e\");","lastModifiedDate":"2025-08-28T16:59:27","isFullCredit":false},{"lineNumber":337,"author":{"gitId":"cjaycee"},"content":"            }","lastModifiedDate":"2025-08-28T16:59:27","isFullCredit":false},{"lineNumber":338,"author":{"gitId":"cjaycee"},"content":"","lastModifiedDate":"2025-08-28T16:59:27","isFullCredit":false},{"lineNumber":339,"author":{"gitId":"cjaycee"},"content":"            int taskNumber \u003d Integer.parseInt(parts[1]) - 1;","lastModifiedDate":"2025-08-28T16:59:27","isFullCredit":false},{"lineNumber":340,"author":{"gitId":"cjaycee"},"content":"","lastModifiedDate":"2025-08-28T16:59:27","isFullCredit":false},{"lineNumber":341,"author":{"gitId":"cjaycee"},"content":"            if (taskNumber \u003c 0 || taskNumber \u003e\u003d tasks.size()) {","lastModifiedDate":"2025-08-28T16:59:27","isFullCredit":false},{"lineNumber":342,"author":{"gitId":"cjaycee"},"content":"                throw new InvalidTaskNumberException(tasks.size());","lastModifiedDate":"2025-08-28T16:59:27","isFullCredit":false},{"lineNumber":343,"author":{"gitId":"cjaycee"},"content":"            }","lastModifiedDate":"2025-08-28T16:59:27","isFullCredit":false},{"lineNumber":344,"author":{"gitId":"cjaycee"},"content":"","lastModifiedDate":"2025-08-28T16:59:27","isFullCredit":false},{"lineNumber":345,"author":{"gitId":"cjaycee"},"content":"            Task removedTask \u003d tasks.remove(taskNumber);","lastModifiedDate":"2025-08-28T16:59:27","isFullCredit":false},{"lineNumber":346,"author":{"gitId":"cjaycee"},"content":"            printLine();","lastModifiedDate":"2025-08-28T16:59:27","isFullCredit":false},{"lineNumber":347,"author":{"gitId":"cjaycee"},"content":"            System.out.println(\"Noted. I\u0027ve removed this task:\");","lastModifiedDate":"2025-08-28T16:59:27","isFullCredit":false},{"lineNumber":348,"author":{"gitId":"cjaycee"},"content":"            System.out.println(\"  \" + removedTask.toString());","lastModifiedDate":"2025-08-28T16:59:27","isFullCredit":false},{"lineNumber":349,"author":{"gitId":"cjaycee"},"content":"            System.out.println(\"Now you have \" + tasks.size() + \" tasks in the list.\");","lastModifiedDate":"2025-08-28T16:59:27","isFullCredit":false},{"lineNumber":350,"author":{"gitId":"cjaycee"},"content":"            printLine();","lastModifiedDate":"2025-08-28T16:59:27","isFullCredit":false},{"lineNumber":351,"author":{"gitId":"cjaycee"},"content":"","lastModifiedDate":"2025-08-28T16:59:27","isFullCredit":false},{"lineNumber":352,"author":{"gitId":"cjaycee"},"content":"        } catch (NumberFormatException e) {","lastModifiedDate":"2025-08-28T16:59:27","isFullCredit":false},{"lineNumber":353,"author":{"gitId":"cjaycee"},"content":"            throw new InvalidFormatException(\"delete \u003ctask-number\u003e (must be a number)\");","lastModifiedDate":"2025-08-28T16:59:27","isFullCredit":false},{"lineNumber":354,"author":{"gitId":"cjaycee"},"content":"        }","lastModifiedDate":"2025-08-28T16:59:27","isFullCredit":false},{"lineNumber":355,"author":{"gitId":"cjaycee"},"content":"    }","lastModifiedDate":"2025-08-28T16:59:27","isFullCredit":false},{"lineNumber":356,"author":{"gitId":"cjaycee"},"content":"}","lastModifiedDate":"2025-08-22T00:25:30","isFullCredit":false}],"authorContributionMap":{"cjaycee":356}},{"path":"text-ui-test/input.txt","fileType":"txt","lines":[{"lineNumber":1,"author":{"gitId":"cjaycee"},"content":"todo borrow book","lastModifiedDate":"2025-08-24T13:43:44","isFullCredit":false},{"lineNumber":2,"author":{"gitId":"cjaycee"},"content":"","lastModifiedDate":"2025-08-24T13:43:44","isFullCredit":false},{"lineNumber":3,"author":{"gitId":"cjaycee"},"content":"deadline return book /by Sunday","lastModifiedDate":"2025-08-24T13:43:44","isFullCredit":false},{"lineNumber":4,"author":{"gitId":"cjaycee"},"content":"","lastModifiedDate":"2025-08-24T13:43:44","isFullCredit":false},{"lineNumber":5,"author":{"gitId":"cjaycee"},"content":"event project meeting /from Mon 2pm /to 4pm","lastModifiedDate":"2025-08-24T13:43:44","isFullCredit":false},{"lineNumber":6,"author":{"gitId":"cjaycee"},"content":"","lastModifiedDate":"2025-08-24T13:43:44","isFullCredit":false},{"lineNumber":7,"author":{"gitId":"cjaycee"},"content":"list","lastModifiedDate":"2025-08-24T13:43:44","isFullCredit":false},{"lineNumber":8,"author":{"gitId":"cjaycee"},"content":"","lastModifiedDate":"2025-08-24T13:43:44","isFullCredit":false},{"lineNumber":9,"author":{"gitId":"cjaycee"},"content":"blah","lastModifiedDate":"2025-08-24T13:43:44","isFullCredit":false},{"lineNumber":10,"author":{"gitId":"cjaycee"},"content":"","lastModifiedDate":"2025-08-24T13:43:44","isFullCredit":false},{"lineNumber":11,"author":{"gitId":"cjaycee"},"content":"todo","lastModifiedDate":"2025-08-24T13:43:44","isFullCredit":false},{"lineNumber":12,"author":{"gitId":"cjaycee"},"content":"","lastModifiedDate":"2025-08-24T13:43:44","isFullCredit":false},{"lineNumber":13,"author":{"gitId":"cjaycee"},"content":"bye","lastModifiedDate":"2025-08-24T13:43:44","isFullCredit":false}],"authorContributionMap":{"cjaycee":13}},{"path":"text-ui-test/runtest.sh","fileType":"sh","lines":[{"lineNumber":1,"author":{"gitId":"-"},"content":"#!/usr/bin/env bash","lastModifiedDate":"2020-05-25T00:03:55","isFullCredit":false},{"lineNumber":2,"author":{"gitId":"-"},"content":"","lastModifiedDate":"2020-05-25T00:03:55","isFullCredit":false},{"lineNumber":3,"author":{"gitId":"-"},"content":"# create bin directory if it doesn\u0027t exist","lastModifiedDate":"2020-05-25T00:03:55","isFullCredit":false},{"lineNumber":4,"author":{"gitId":"-"},"content":"if [ ! -d \"../bin\" ]","lastModifiedDate":"2020-05-25T00:03:55","isFullCredit":false},{"lineNumber":5,"author":{"gitId":"-"},"content":"then","lastModifiedDate":"2020-05-25T00:03:55","isFullCredit":false},{"lineNumber":6,"author":{"gitId":"-"},"content":"    mkdir ../bin","lastModifiedDate":"2020-05-25T00:03:55","isFullCredit":false},{"lineNumber":7,"author":{"gitId":"-"},"content":"fi","lastModifiedDate":"2020-05-25T00:03:55","isFullCredit":false},{"lineNumber":8,"author":{"gitId":"-"},"content":"","lastModifiedDate":"2020-05-25T00:03:55","isFullCredit":false},{"lineNumber":9,"author":{"gitId":"-"},"content":"# delete output from previous run","lastModifiedDate":"2020-05-25T00:03:55","isFullCredit":false},{"lineNumber":10,"author":{"gitId":"-"},"content":"if [ -e \"./ACTUAL.TXT\" ]","lastModifiedDate":"2020-05-25T00:03:55","isFullCredit":false},{"lineNumber":11,"author":{"gitId":"-"},"content":"then","lastModifiedDate":"2020-05-25T00:03:55","isFullCredit":false},{"lineNumber":12,"author":{"gitId":"-"},"content":"    rm ACTUAL.TXT","lastModifiedDate":"2020-05-25T00:03:55","isFullCredit":false},{"lineNumber":13,"author":{"gitId":"-"},"content":"fi","lastModifiedDate":"2020-05-25T00:03:55","isFullCredit":false},{"lineNumber":14,"author":{"gitId":"-"},"content":"","lastModifiedDate":"2020-05-25T00:03:55","isFullCredit":false},{"lineNumber":15,"author":{"gitId":"-"},"content":"# compile the code into the bin folder, terminates if error occurred","lastModifiedDate":"2020-05-25T00:03:55","isFullCredit":false},{"lineNumber":16,"author":{"gitId":"-"},"content":"if ! javac -cp ../src/main/java -Xlint:none -d ../bin ../src/main/java/*.java","lastModifiedDate":"2020-08-25T17:23:26","isFullCredit":false},{"lineNumber":17,"author":{"gitId":"-"},"content":"then","lastModifiedDate":"2020-05-25T00:03:55","isFullCredit":false},{"lineNumber":18,"author":{"gitId":"-"},"content":"    echo \"********** BUILD FAILURE **********\"","lastModifiedDate":"2020-05-25T00:03:55","isFullCredit":false},{"lineNumber":19,"author":{"gitId":"-"},"content":"    exit 1","lastModifiedDate":"2020-05-25T00:03:55","isFullCredit":false},{"lineNumber":20,"author":{"gitId":"-"},"content":"fi","lastModifiedDate":"2020-05-25T00:03:55","isFullCredit":false},{"lineNumber":21,"author":{"gitId":"-"},"content":"","lastModifiedDate":"2020-05-25T00:03:55","isFullCredit":false},{"lineNumber":22,"author":{"gitId":"-"},"content":"# run the program, feed commands from input.txt file and redirect the output to the ACTUAL.TXT","lastModifiedDate":"2020-05-25T00:03:55","isFullCredit":false},{"lineNumber":23,"author":{"gitId":"cjaycee"},"content":"java -classpath ../bin Usagi \u003c input.txt \u003e ACTUAL.TXT","lastModifiedDate":"2025-08-22T12:17:54","isFullCredit":false},{"lineNumber":24,"author":{"gitId":"-"},"content":"","lastModifiedDate":"2020-05-25T00:03:55","isFullCredit":false},{"lineNumber":25,"author":{"gitId":"-"},"content":"# compare the output to the expected output","lastModifiedDate":"2020-05-25T00:03:55","isFullCredit":false},{"lineNumber":26,"author":{"gitId":"cjaycee"},"content":"diff ACTUAL.TXT EXPECTED.TXT","lastModifiedDate":"2025-08-22T12:17:54","isFullCredit":false},{"lineNumber":27,"author":{"gitId":"-"},"content":"if [ $? -eq 0 ]","lastModifiedDate":"2020-05-25T00:03:55","isFullCredit":false},{"lineNumber":28,"author":{"gitId":"-"},"content":"then","lastModifiedDate":"2020-05-25T00:03:55","isFullCredit":false},{"lineNumber":29,"author":{"gitId":"-"},"content":"    echo \"Test result: PASSED\"","lastModifiedDate":"2020-05-25T00:03:55","isFullCredit":false},{"lineNumber":30,"author":{"gitId":"-"},"content":"    exit 0","lastModifiedDate":"2020-05-25T00:03:55","isFullCredit":false},{"lineNumber":31,"author":{"gitId":"-"},"content":"else","lastModifiedDate":"2020-05-25T00:03:55","isFullCredit":false},{"lineNumber":32,"author":{"gitId":"-"},"content":"    echo \"Test result: FAILED\"","lastModifiedDate":"2020-05-25T00:03:55","isFullCredit":false},{"lineNumber":33,"author":{"gitId":"-"},"content":"    exit 1","lastModifiedDate":"2020-05-25T00:03:55","isFullCredit":false},{"lineNumber":34,"author":{"gitId":"-"},"content":"fi","lastModifiedDate":"2020-05-25T00:03:55","isFullCredit":false}],"authorContributionMap":{"-":32,"cjaycee":2}}]
